contact_user_external_local/__init__.py
contact_user_external_local/contact_user_external_local.py
contact_user_external_local/contact_user_external_local_constants.py
contact_user_external_local-0.0.13.dist-info/METADATA
contact_user_external_local-0.0.13.dist-info/WHEEL
contact_user_external_local-0.0.13.dist-info/top_level.txt
contact_user_external_local-0.0.13.dist-info/RECORD
